LICENSE
MANIFEST.in
README.rst
setup.py
django_api/__init__.py
django_api/decorators.py
django_api/json_helpers.py
django_api/models.py
django_api/tests.py
django_api.egg-info/PKG-INFO
django_api.egg-info/SOURCES.txt
django_api.egg-info/dependency_links.txt
django_api.egg-info/top_level.txt