Metadata-Version: 1.1
Name: django-api
Version: 0.1.3
Summary: Specify and validate your Django APIs
Home-page: https://github.com/bipsandbytes/django-api
Author: Bipin Suresh
Author-email: bipins@alumni.stanford.edu
License: BSD License
Platform: UNKNOWN
Classifier: Environment :: Web Environment
Classifier: Framework :: Django
Classifier: Intended Audience :: Developers
Classifier: License :: OSI Approved :: BSD License
Classifier: Operating System :: OS Independent
Classifier: Programming Language :: Python
Classifier: Topic :: Internet :: WWW/HTTP
Classifier: Topic :: Internet :: WWW/HTTP :: Dynamic Content
